{
  "cart_path": "/home/siah/creative/reactjit/tsz/carts/conformance/mixed/d102_effect_color_indexing.tsz",
  "lane": "mixed",
  "legacy_hash": "a25ea0dac5e65c0a57b1ef8826d23d29fe07f3ad7390a83829775f6652f88ef1",
  "atom_hash": "e4c7a1ff0f76570716a961a519ed76ae31cdbc0d798e970d09f548166f7d4dac",
  "diff_status": "DIFF",
  "first_diff_hunk": "--- legacy line 17 ---\n  comptime { _ = @import(\"framework/core.zig\"); }\n  \n> // ── Generated node tree ─────────────────────────────────────────\n  // tsz:d102_effect_color_indexing.tsz:8 — <Box>\n  var _arr_0 = [_]Node{ .{ .text = \"D102 Effect Color Indexing\", .font_size = 16, .text_color = Color.rgb(248, 250, 252) }, .{ .text = \"Top panel should be a full hue gradient. Bottom panel should show coral, aqua, and violet pastel bands.\", .font_size = 10, .text_color = Color.rgb(148, 163, 184) }, .{ .style = .{ .width = 320, .height = 150 }, .effect_render = _effect_render_0, .effect_shader = _effect_shader_0 }, .{ .style = .{ .width = 320, .height = 64 }, .effect_render = _effect_render_1, .effect_shader = _effect_shader_1 } };\n+++ atom line 17 +++\n  comptime { _ = @import(\"framework/core.zig\"); }\n  \n> fn _initState() void {\n  }\n  \n",
  "split_output": true,
  "backend_tags": [
    "effects"
  ],
  "predicted_atoms": [],
  "verification_time": "2026-04-09T09:46:15.132Z",
  "legacy_error": null,
  "atom_error": null,
  "legacy_files": [
    "app.zig",
    "handlers.zig",
    "logic.zig",
    "maps.zig",
    "nodes.zig",
    "state.zig"
  ]
}
